odoo8_addon_stock_available_mrp-8.0.3.1.1-py2.7-nspkg.pth
odoo_addons/stock_available_mrp/__openerp__.py
odoo_addons/stock_available_mrp/__init__.py
odoo_addons/stock_available_mrp/README.rst
odoo_addons/stock_available_mrp/models/product_template.py
odoo_addons/stock_available_mrp/models/product_product.py
odoo_addons/stock_available_mrp/models/__init__.py
odoo_addons/stock_available_mrp/i18n/it.po
odoo_addons/stock_available_mrp/i18n/es.po
odoo_addons/stock_available_mrp/i18n/sl.po
odoo_addons/stock_available_mrp/i18n/de.po
odoo_addons/stock_available_mrp/i18n/stock_available_mrp.pot
odoo_addons/stock_available_mrp/i18n/fr.po
odoo_addons/stock_available_mrp/i18n/fi.po
odoo_addons/stock_available_mrp/views/product_template_view.xml
odoo_addons/stock_available_mrp/tests/__init__.py
odoo_addons/stock_available_mrp/tests/test_potential_qty.py
odoo_addons/stock_available_mrp/demo/mrp_bom.yml
odoo8_addon_stock_available_mrp-8.0.3.1.1.dist-info/top_level.txt
odoo8_addon_stock_available_mrp-8.0.3.1.1.dist-info/WHEEL
odoo8_addon_stock_available_mrp-8.0.3.1.1.dist-info/RECORD
odoo8_addon_stock_available_mrp-8.0.3.1.1.dist-info/metadata.json
odoo8_addon_stock_available_mrp-8.0.3.1.1.dist-info/DESCRIPTION.rst
odoo8_addon_stock_available_mrp-8.0.3.1.1.dist-info/METADATA
odoo8_addon_stock_available_mrp-8.0.3.1.1.dist-info/namespace_packages.txt
